AUTHORS
LICENSE
MANIFEST.in
README
requirements.txt
setup.py
configreset/__init__.py
configreset/parameter.py
configreset.egg-info/PKG-INFO
configreset.egg-info/SOURCES.txt
configreset.egg-info/dependency_links.txt
configreset.egg-info/requires.txt
configreset.egg-info/top_level.txt