Metadata-Version: 1.0
Name: configreset
Version: 1.0.2
Summary: configreset
Home-page: https://github.com/lvjiyong/configreset
Author: lvjiyong
Author-email: lvjiyong@gmail.com
License: GPL
Platform: any
